.gitignore
.travis.yml
AUTHORS.rst
CHANGELOG.rst
Dockerfile
LICENSE
MANIFEST.in
Makefile
README.rst
docker-compose.yml
setup.cfg
setup.py
bin/docker-entrypoint
bin/wait-for-it.sh
src/redash_stmo/__init__.py
src/redash_stmo/api_endpoint.py
src/redash_stmo/dockerflow.py
src/redash_stmo/health.py
src/redash_stmo/optimizer_endpoint.py
src/redash_stmo/settings.py
src/redash_stmo/query_runner/__init__.py
src/redash_stmo/query_runner/activedata.py
src/redash_stmo_swathi.egg-info/PKG-INFO
src/redash_stmo_swathi.egg-info/SOURCES.txt
src/redash_stmo_swathi.egg-info/dependency_links.txt
src/redash_stmo_swathi.egg-info/entry_points.txt
src/redash_stmo_swathi.egg-info/not-zip-safe
src/redash_stmo_swathi.egg-info/requires.txt
src/redash_stmo_swathi.egg-info/top_level.txt
tests/test_health.py